{
  "notes": [
    {
      "id": 1,
      "title": "First Task",
      "text": "Use Services"
    },
    {
      "id": 2,
      "title": "asa",
      "text": "asasasasas"
    },
    {
      "id": 3,
      "title": "ddsd",
      "text": "sdsds"
    },
    {
      "id": 4,
      "title": "dsd",
      "text": "dfdsf"
    },
    {
      "id": 5,
      "title": "dsadsa",
      "text": "sadsa"
    },
    {
      "id": 6,
      "title": "dsd",
      "text": "sadsa"
    },
    {
      "id": 7,
      "title": "sdsad",
      "text": "sadsad"
    },
    {
      "id": 8,
      "title": "sadsa",
      "text": "sdsadsa"
    },
    {
      "id": 9,
      "title": "sadsdsadasdsa",
      "text": "asdsadsadsad"
    },
    {
      "id": 10,
      "title": "asdsadas",
      "text": "asdsadsa"
    },
    {
      "id": 11,
      "title": "asdsad",
      "text": "dsfdsfds"
    },
    {
      "id": 12,
      "title": "dsfdsf",
      "text": "dsfdsfdsfsd"
    },
    {
      "id": 13,
      "title": "dfdsfsd",
      "text": "dsfdsf"
    },
    {
      "id": 14,
      "title": "sasa",
      "text": "AsaS"
    },
    {
      "id": 15,
      "title": "SADSA",
      "text": "SADSA"
    },
    {
      "id": 16,
      "title": "SDSA",
      "text": "ASDSA"
    },
    {
      "id": 17,
      "title": "SDSA",
      "text": "SADSA"
    }
  ]
}